advanced_ta/LorentzianClassification/Classifier.py
advanced_ta/LorentzianClassification/KernelFunctions.py
advanced_ta/LorentzianClassification/MLExtensions.py
advanced_ta/LorentzianClassification/Types.py
advanced_ta/Utils.py
advanced_ta/__init__.py
advanced_ta-0.1.8.dist-info/METADATA
advanced_ta-0.1.8.dist-info/WHEEL
advanced_ta-0.1.8.dist-info/RECORD
