Metadata-Version: 2.1
Name: advanced-ta
Version: 0.1.8
Summary: Python implementation of Lorentzian Classification algorithm.
Home-page: https://bitbucket.org/lokiarya/advanced-ta
Author: Loki Arya
Author-email: loki.arya+osdev@gmail.com
Requires-Python: >=3.10,<4.0
Classifier: Programming Language :: Python :: 3
Classifier: Programming Language :: Python :: 3.10
Classifier: Programming Language :: Python :: 3.11
Requires-Dist: mplfinance (>=0.12.9-beta.7,<0.13.0)
Requires-Dist: numpy (>=1.25.1,<2.0.0)
Requires-Dist: pandas (>=2.0.3,<3.0.0)
Requires-Dist: python-dotenv (>=1.0.0,<2.0.0)
Requires-Dist: scikit-learn (>=1.3.0,<2.0.0)
Requires-Dist: ta (>=0.11.0,<0.12.0)
Project-URL: Repository, https://bitbucket.org/lokiarya/advanced-ta
